[
    {
        "_id": "655c3c1f3613e949b4d61d5c",
        "menuItemId": "64a6c1e33339d4dc9d8141aa",
        "module": "Dispatch",
        "type": "TRANSACTION",
        "order": 1,
        "isDisplay": false,
        "title": "Shipment Planning",
        "displayName": "Shipment Planning",
        "disabled": false,
        "url": "/default/dispatch/transactions/shipment_creation/list",
        "items": [],
        "roles": []
    },
    {
        "_id": "655c3c1f3613e949b4d61d64",
        "menuItemId": "64a6c1e33339d4dc9d8141aa",
        "module": "Dispatch",
        "type": "TRANSACTION",
        "order": 2,
        "isDisplay": false,
        "title": "Tax Invoice",
        "displayName": "Tax Invoice",
        "disabled": false,
        "url": "/default/dispatch/transactions/tax_invoice",
        "items": [],
        "roles": []
    },
    {
        "_id": "6517baf65dfcccfabbc5d462",
        "menuItemId": "64a6c1e33339d4dc9d8141aa",
        "module": "Dispatch",
        "type": "TRANSACTION",
        "order": 3,
        "isDisplay": false,
        "title": "Generate E-Way Bill",
        "displayName": "Generate E-Way Bill",
        "disabled": false,
        "url": "/default/dispatch/transactions/generate_e_way_bills",
        "items": [],
        "roles": []
    },
    {
        "_id": "64e87e3165abe8d07ede8f20",
        "menuItemId": "64a6c1e33339d4dc9d8141aa",
        "module": "Dispatch",
        "type": "TRANSACTION",
        "order": 4,
        "isDisplay": false,
        "title": "Generate E-Invoice",
        "displayName": "Generate E-Invoice",
        "disabled": false,
        "url": "/default/dispatch/transactions/generate-e-invoice",
        "items": [],
        "roles": []
    },
    {
        "_id": "655c3c1f3613e949b4d61d6c",
        "menuItemId": "64a6c1e33339d4dc9d8141aa",
        "module": "Dispatch",
        "type": "TRANSACTION",
        "order": 5,
        "isDisplay": false,
        "title": "Advance Shipment Notice",
        "displayName": "Advance Shipment Notice",
        "disabled": false,
        "url": "/default/dispatch/transactions/asn/list",
        "items": [],
        "roles": []
    },
    {
        "_id": "655c3c1f3613e949b4d61d75",
        "menuItemId": "64a6c1e33339d4dc9d8141aa",
        "module": "Dispatch",
        "type": "TRANSACTION",
        "order": 6,
        "isDisplay": false,
        "title": "Goods Requisition",
        "displayName": "Goods Requisition",
        "disabled": false,
        "url": "/default/dispatch/transactions/grl/list",
        "items": [],
        "roles": []
    },

    {
        "_id": "65b4da1cbfc65957035c4fee",
        "menuItemId": "64a6c1e33339d4dc9d8141aa",
        "module": "Dispatch",
        "type": "TRANSACTION",
        "order": 7,
        "isDisplay": false,
        "title": "Generate Export E-Way Bill",
        "displayName": "Generate Export E-Way Bill",
        "disabled": false,
        "url": "/default/dispatch/transactions/generate_export_e_way_bills",
        "items": [],
        "roles": []
    },
    {
        "_id": "65b4d0b311f01bd22b94e089",
        "menuItemId": "64a6c1e33339d4dc9d8141aa",
        "module": "Dispatch",
        "type": "TRANSACTION",
        "order": 8,
        "isDisplay": false,
        "title": "Generate Export E-Invoice",
        "displayName": "Generate Export E-Invoice",
        "disabled": false,
        "url": "/default/dispatch/transactions/generate_export_e_invoice",
        "items": [],
        "roles": []
    }
]
